pacifica_ingest-0.4.1-py3.8-nspkg.pth
pacifica/ingest/__init__.py
pacifica/ingest/__main__.py
pacifica/ingest/config.py
pacifica/ingest/globals.py
pacifica/ingest/orm.py
pacifica/ingest/rest.py
pacifica/ingest/tarutils.py
pacifica/ingest/tasks.py
pacifica/ingest/utils.py
pacifica/ingest/wsgi.py
pacifica_ingest-0.4.1.dist-info/LICENSE
pacifica_ingest-0.4.1.dist-info/METADATA
pacifica_ingest-0.4.1.dist-info/WHEEL
pacifica_ingest-0.4.1.dist-info/entry_points.txt
pacifica_ingest-0.4.1.dist-info/namespace_packages.txt
pacifica_ingest-0.4.1.dist-info/top_level.txt
pacifica_ingest-0.4.1.dist-info/RECORD
