Metadata-Version: 2.1
Name: pacifica-ingest
Version: 0.4.1
Summary: Pacifica Ingest
Home-page: https://github.com/pacifica/pacifica-ingest/
Author: David Brown
Author-email: david.brown@pnnl.gov
License: UNKNOWN
Platform: UNKNOWN
Requires-Dist: celery
Requires-Dist: cherrypy
Requires-Dist: peewee (>2)
Requires-Dist: requests
